npblob-0.0.1.dist-info/METADATA
npblob-0.0.1.dist-info/WHEEL
npblob-0.0.1.dist-info/licenses/LICENSE
npblob/__init__.py
npblob/encode.py
npblob-0.0.1.dist-info/RECORD
